minervaclient/__init__.py
minervaclient/__main__.py
minervaclient/auth_search.py
minervaclient/auth_search_parse.py
minervaclient/config.py
minervaclient/credentials.py
minervaclient/ecalendar_search.py
minervaclient/exams.py
minervaclient/exams_ics.py
minervaclient/exams_parse.py
minervaclient/mercury_search.py
minervaclient/minerva_common.py
minervaclient/pub_search.py
minervaclient/reg.py
minervaclient/reg_parse.py
minervaclient/sched.py
minervaclient/sched_ics.py
minervaclient/sched_parse.py
minervaclient/sched_timetable.css
minervaclient/sched_timetable.py
minervaclient/transcript.py
minervaclient/transcript_parse.py
minervaclient-1.3.0.data/scripts/minervac
minervaclient-1.3.0.data/scripts/minervac.bat
minervaclient-1.3.0.dist-info/DESCRIPTION.rst
minervaclient-1.3.0.dist-info/METADATA
minervaclient-1.3.0.dist-info/RECORD
minervaclient-1.3.0.dist-info/WHEEL
minervaclient-1.3.0.dist-info/dependency_links.txt
minervaclient-1.3.0.dist-info/metadata.json
minervaclient-1.3.0.dist-info/top_level.txt
