Metadata-Version: 2.0
Name: minervaclient
Version: 1.3.0
Summary: Tools and Utilities that can be used to access McGill University's Minerva service
Home-page: https://github.com/auryan898/minervaclient
Author: Ryan B Au
Author-email: auryan898@gmail.com
License: MIT
Download-URL: https://github.com/auryan898/minervaclient/archive/master.zip
Keywords: minerva,banner,mcgill,college,schedule
Platform: UNKNOWN
Provides-Extra: full_cli_support
Provides-Extra: html5_parse
Requires-Dist: beautifulsoup4
Requires-Dist: requests
Provides-Extra: full_cli_support
Requires-Dist: keyring; extra == 'full_cli_support'
Requires-Dist: keyrings.cryptfile; extra == 'full_cli_support'
Provides-Extra: html5_parse
Requires-Dist: html5lib; extra == 'html5_parse'
